[
  {
    "model": "store.ChangeReason",
    "pk": "043dee8b-afca-44c3-affb-6eabcaf4366e",
    "fields": {
      "reason": "Closing an open record"
    }
  },
  {
    "model": "store.ChangeReason",
    "pk": "1772f5ca-87a7-425b-9445-34eaf0083290",
    "fields": {
      "reason": "Correction"
    }
  },
  {
    "model": "store.ChangeReason",
    "pk": "2b5a8e28-f6ea-40ec-ad65-ca91bda8ccf2",
    "fields": {
      "reason": "Opening date later after FOI review"
    }
  },
  {
    "model": "store.ChangeReason",
    "pk": "3fe3c78c-5514-4e82-949e-1b88d6120f90",
    "fields": {
      "reason": "Ingest Closure"
    }
  },
  {
    "model": "store.ChangeReason",
    "pk": "47bbcf0c-384a-4bfe-a92f-1db791758e24",
    "fields": {
      "reason": "Opening date earlier after FOI review"
    }
  },
  {
    "model": "store.ChangeReason",
    "pk": "4954be50-8583-4aa1-b0d0-1a8d80b43329",
    "fields": {
      "reason": "Birth+marriage certificate record opening earlier"
    }
  },
  {
    "model": "store.ChangeReason",
    "pk": "5868b566-b3f7-49e5-976e-42bae9e2bb59",
    "fields": {
      "reason": "Legacy: opening date later to match SAR"
    }
  },
  {
    "model": "store.ChangeReason",
    "pk": "5c7f0f1c-c9d0-4942-95c1-3463f63018a4",
    "fields": {
      "reason": "Record opened after review"
    }
  },
  {
    "model": "store.ChangeReason",
    "pk": "8583dcb1-9465-4f72-86fd-c73bbf1be916",
    "fields": {
      "reason": "Legacy: record opened to match SAR"
    }
  },
  {
    "model": "store.ChangeReason",
    "pk": "858b8791-80ee-453d-b0d5-70be693dd61e",
    "fields": {
      "reason": "Sparql cleanup activity"
    }
  },
  {
    "model": "store.ChangeReason",
    "pk": "924785a0-6275-4a6e-89ed-f011ae8fdebe",
    "fields": {
      "reason": "Closure Update"
    }
  },
  {
    "model": "store.ChangeReason",
    "pk": "95760c91-0aad-41f5-a54e-ae8b0531ed82",
    "fields": {
      "reason": "Death+marriage certificate record opening"
    }
  },
  {
    "model": "store.ChangeReason",
    "pk": "9db26ba4-2058-4fea-8c8f-0fc527f8bd24",
    "fields": {
      "reason": "Opened on export"
    }
  },
  {
    "model": "store.ChangeReason",
    "pk": "9ff9605a-14ec-4be8-8396-316aded86334",
    "fields": {
      "reason": "Birth+marriage certificate record opening"
    }
  },
  {
    "model": "store.ChangeReason",
    "pk": "a7d669c4-e3a0-4f0e-95aa-dc8cef8ef8cf",
    "fields": {
      "reason": "Opening a closed title or description"
    }
  },
  {
    "model": "store.ChangeReason",
    "pk": "a823ba2d-7eff-455d-951f-e48b28e966a6",
    "fields": {
      "reason": "Closing an open title or description"
    }
  },
  {
    "model": "store.ChangeReason",
    "pk": "b674f54c-f0fb-11ea-adc1-0242ac120002",
    "fields": {
      "reason": "Birth+marriage certificate record opening later"
    }
  },
  {
    "model": "store.ChangeReason",
    "pk": "bb2194d1-3c4e-4ea1-8a53-2d99b16311a9",
    "fields": {
      "reason": "FOI code amended after review"
    }
  },
  {
    "model": "store.ChangeReason",
    "pk": "f0c76bc6-1f56-44d1-bb02-d2cea8a1994e",
    "fields": {
      "reason": "Legacy: opening date earlier to match SAR"
    }
  }
]
